hpcyhr/__init__.py
hpcyhr/yhr.py
hpcyhr-1.0.dist-info/LICENSE
hpcyhr-1.0.dist-info/METADATA
hpcyhr-1.0.dist-info/WHEEL
hpcyhr-1.0.dist-info/top_level.txt
hpcyhr-1.0.dist-info/RECORD
