Metadata-Version: 2.1
Name: hpcyhr
Version: 1.0
Summary: 一个没有啥用的包
Author: yanghongru
Author-email: hpcyhr@163.com
Classifier: Programming Language :: Python :: 3
Classifier: License :: OSI Approved :: MIT License
Classifier: Operating System :: OS Independent
Requires-Python: >=3
License-File: LICENSE
Requires-Dist: requests
